aana/__init__.py
aana/alembic/README
aana/alembic/__init__.py
aana/alembic/env.py
aana/alembic/script.py.mako
aana/alembic/versions/5ad873484aa3_init.py
aana/alembic/versions/b9860676dd49_set_server_default_for_task_completed_.py
aana/alembic.ini
aana/api/__init__.py
aana/api/api_generation.py
aana/api/app.py
aana/api/event_handlers/event_handler.py
aana/api/event_handlers/event_manager.py
aana/api/event_handlers/rate_limit_handler.py
aana/api/exception_handler.py
aana/api/request_handler.py
aana/api/responses.py
aana/cli.py
aana/configs/__init__.py
aana/configs/db.py
aana/configs/settings.py
aana/core/__init__.py
aana/core/chat/chat_template.py
aana/core/chat/templates/__init__.py
aana/core/chat/templates/llama2.jinja
aana/core/libraries/audio.py
aana/core/libraries/image.py
aana/core/models/__init__.py
aana/core/models/api.py
aana/core/models/asr.py
aana/core/models/audio.py
aana/core/models/base.py
aana/core/models/captions.py
aana/core/models/chat.py
aana/core/models/custom_config.py
aana/core/models/exception.py
aana/core/models/file.py
aana/core/models/image.py
aana/core/models/image_chat.py
aana/core/models/media.py
aana/core/models/sampling.py
aana/core/models/speaker.py
aana/core/models/task.py
aana/core/models/time.py
aana/core/models/types.py
aana/core/models/vad.py
aana/core/models/video.py
aana/core/models/whisper.py
aana/deployments/__init__.py
aana/deployments/aana_deployment_handle.py
aana/deployments/base_deployment.py
aana/deployments/base_text_generation_deployment.py
aana/deployments/haystack_component_deployment.py
aana/deployments/hf_blip2_deployment.py
aana/deployments/hf_pipeline_deployment.py
aana/deployments/hf_text_generation_deployment.py
aana/deployments/hqq_text_generation_deployment.py
aana/deployments/idefics_2_deployment.py
aana/deployments/pyannote_speaker_diarization_deployment.py
aana/deployments/sentence_transformer_deployment.py
aana/deployments/task_queue_deployment.py
aana/deployments/vad_deployment.py
aana-0.2.3.dist-info/LICENSE
aana-0.2.3.dist-info/METADATA
aana-0.2.3.dist-info/WHEEL
aana-0.2.3.dist-info/entry_points.txt
aana-0.2.3.dist-info/RECORD
