Metadata-Version: 2.1
Name: aana
Version: 0.2.3
Summary: Multimodal SDK
Home-page: https://www.mobiuslabs.com
License: Apache-2.0
Keywords: multimodal,ray,serving,video,images,audio,llm,vlm,asr
Author: Mobius Labs GmbH
Author-email: dev@mobiuslabs.com
Requires-Python: >=3.10,<4.0
Classifier: Intended Audience :: Developers
Classifier: Intended Audience :: Science/Research
Classifier: License :: OSI Approved :: Apache Software License
Classifier: Operating System :: OS Independent
Classifier: Programming Language :: Python :: 3
Classifier: Programming Language :: Python :: 3.10
Classifier: Programming Language :: Python :: 3.11
Classifier: Programming Language :: Python :: 3.12
Classifier: Programming Language :: Python :: 3.13
Classifier: Topic :: Scientific/Engineering :: Artificial Intelligence
Requires-Dist: accelerate (>=0.34.2,<0.35.0)
Requires-Dist: alembic (>=1.12.1,<2.0.0)
Requires-Dist: av (==11.*)
Requires-Dist: bitblas (>=0.0.1.dev15,<0.0.2)
Requires-Dist: bitsandbytes (>=0.42.0,<0.43.0)
Requires-Dist: decord (>=0.6.0,<0.7.0)
Requires-Dist: fastapi (>=0.111.0)
Requires-Dist: haystack-ai (>=2.1.0)
Requires-Dist: hf-transfer (>=0.1.6,<0.2.0)
Requires-Dist: hqq (>=0.2.2,<0.3.0)
Requires-Dist: mobius-faster-whisper (>=1.1.1)
Requires-Dist: numpy (>=1.17,<2)
Requires-Dist: opencv-python-headless (>=4.8.1.78,<5.0.0.0)
Requires-Dist: orjson (>=3.10.3,<4.0.0)
Requires-Dist: outlines[serve] (>=0.0.46,<0.0.47)
Requires-Dist: portpicker (>=1.6.0,<2.0.0)
Requires-Dist: psycopg[binary] (>=3.2.1,<4.0.0)
Requires-Dist: pyannote-audio (>=3.1.1,<4.0.0)
Requires-Dist: pydantic (>=2.0)
Requires-Dist: pydantic-settings (>=2.1.0,<3.0.0)
Requires-Dist: python-multipart (>=0.0.9,<0.0.10)
Requires-Dist: qdrant-haystack (>=3.2.0)
Requires-Dist: rapidfuzz (>=3.4.0,<4.0.0)
Requires-Dist: ray[serve] (>=2.20)
Requires-Dist: scipy (>=1.11.3,<2.0.0)
Requires-Dist: sentence-transformers (>=2.6.1)
Requires-Dist: sqlalchemy[mypy] (>=2.0.23,<3.0.0)
Requires-Dist: torch (>=2.4.0,<3.0.0)
Requires-Dist: torchaudio (>=2.4.0)
Requires-Dist: torchvision (>=0.19.0)
Requires-Dist: transformers (>=4.44.2)
Requires-Dist: vllm (>=0.6.1,<0.6.4)
Requires-Dist: yt-dlp (>=2024.08.06)
Project-URL: Documentation, https://mobiusml.github.io/aana_sdk
Project-URL: Repository, https://github.com/mobiusml/aana_sdk
